P2S/design.sv
module P2S (
    input  logic        SCLK,      // System clock (26.88 MHz)
    input  logic        LOAD,      // Load 40-bit parallel data (active high)
    input  logic        CLR,       // Clear signal (active high)
    input  logic [39:0] PDATAIN,   // 40-bit parallel input (MSB-first: PDATAIN[0] = sign bit)
    output logic        DATAOUT,   // Serial output (MSB-first)
    output logic        OutReady   // High during 40-cycle transmission
);

    // Internal shift register and counter
    logic [39:0] shift_reg;  // MSB at shift_reg[0], LSB at shift_reg[39]
    logic [5:0]  count;      // Counts 0-39 (6 bits)

    always_ff @(posedge SCLK or posedge CLR) begin
        if (CLR) begin
            shift_reg <= 40'h0;
            count     <= 6'd40;  // Initialize to 40 (OutReady = 0)
        end else if (LOAD) begin
            // Load parallel data and start transmission
            shift_reg <= PDATAIN;
            count     <= 6'd0;   // Reset counter (OutReady = 1)
        end else if (count < 6'd40) begin
            // Shift right to transmit MSB-first
            shift_reg <= {shift_reg[38:0], 1'b0};
            count     <= count + 1;
        end
    end
    

    // Output logic
    assign DATAOUT = shift_reg[39];    // MSB (sign bit) first
    assign OutReady = (count < 6'd40); // High during 40-bit transmission

endmodule

P2S/tb.sv
`timescale 1ns / 1ps

module tb_P2S();

    // Inputs
    logic SCLK;          // System clock (26.88 MHz)
    logic LOAD;         // LOAD synchronization
    logic CLR;           // Clear signal
    logic [39:0] PDATAIN; // 40-bit parallel input

    // Outputs
    logic DATAOUT;       // Serial output
    logic OutReady;      // Transmission status

    // Instantiate the P2S module
    P2S uut (
        .SCLK(SCLK),
        .LOAD(LOAD),
        .CLR(CLR),
        .PDATAIN(PDATAIN),
        .DATAOUT(DATAOUT),
        .OutReady(OutReady)
    );

    // Generate SCLK (26.88 MHz, period ≈ 37.2 ns)
    initial begin
        SCLK = 0;
        forever #18.6 SCLK = ~SCLK; // Half-period = 18.6 ns
    end

    // Test sequence
    initial begin
        // Initialize inputs
        CLR = 1;
        LOAD = 0;
        PDATAIN = 40'hA5A5A5A5A5; // Test pattern: alternating 1s and 0s (MSB=1)

        // Apply reset
        #100;
        CLR = 0;

        // Trigger LOAD to start transmission
        @(posedge SCLK);
        LOAD = 1;
        @(posedge SCLK);
        LOAD = 0;

        // Monitor transmission
        $display("Starting transmission...");
        for (int i = 0; i < 40; i++) begin
            @(negedge SCLK); // Check outputs at clock edge
            $display("Cycle %0d: DATAOUT = %b, OutReady = %b", i, DATAOUT, OutReady);

        end


        #100;

        $display("Transmission completed successfully!");
        $finish;
    end

    initial begin
        $dumpfile("tb.vcd");
        $dumpvars(0, tb_P2S);
    end

endmodule

P2S/tb.vcd
$version Generated by VerilatedVcd $end
$timescale 1ps $end
 $scope module $rootio $end
 $upscope $end
 $scope module tb_P2S $end
  $var wire 1 ( SCLK $end
  $var wire 1 ) LOAD $end
  $var wire 1 * CLR $end
  $var wire 40 + PDATAIN [39:0] $end
  $var wire 1 # DATAOUT $end
  $var wire 1 $ OutReady $end
  $scope module unnamedblk1 $end
   $var wire 32 - i [31:0] $end
  $upscope $end
  $scope module uut $end
   $var wire 1 ( SCLK $end
   $var wire 1 ) LOAD $end
   $var wire 1 * CLR $end
   $var wire 40 + PDATAIN [39:0] $end
   $var wire 1 # DATAOUT $end
   $var wire 1 $ OutReady $end
   $var wire 40 % shift_reg [39:0] $end
   $var wire 6 ' count [5:0] $end
  $upscope $end
 $upscope $end
$enddefinitions $end


#0
0#
1$
b0000000000000000000000000000000000000000 %
b000000 '
0(
0)
1*
b1010010110100101101001011010010110100101 +
b00000000000000000000000000000000 -
#18600
0$
b101000 '
1(
#37200
0(
#55800
1(
#74400
0(
#93000
1(
#100000
0*
#111600
0(
#130200
1#
1$
b1010010110100101101001011010010110100101 %
b000000 '
1(
1)
#148800
0(
#167400
0#
b0101001011010010110100101101001011010010 %
b000001 '
1(
0)
#186000
0(
b00000000000000000000000000000001 -
#204600
1#
b0010100101101001011010010110100101101001 %
b000010 '
1(
#223200
0(
b00000000000000000000000000000010 -
#241800
0#
b0001010010110100101101001011010010110100 %
b000011 '
1(
#260400
0(
b00000000000000000000000000000011 -
#279000
b0000101001011010010110100101101001011010 %
b000100 '
1(
#297600
0(
b00000000000000000000000000000100 -
#316200
1#
b0000010100101101001011010010110100101101 %
b000101 '
1(
#334800
0(
b00000000000000000000000000000101 -
#353400
0#
b0000001010010110100101101001011010010110 %
b000110 '
1(
#372000
0(
b00000000000000000000000000000110 -
#390600
1#
b0000000101001011010010110100101101001011 %
b000111 '
1(
#409200
0(
b00000000000000000000000000000111 -
#427800
b0000000010100101101001011010010110100101 %
b001000 '
1(
#446400
0(
b00000000000000000000000000001000 -
#465000
0#
b0000000001010010110100101101001011010010 %
b001001 '
1(
#483600
0(
b00000000000000000000000000001001 -
#502200
1#
b0000000000101001011010010110100101101001 %
b001010 '
1(
#520800
0(
b00000000000000000000000000001010 -
#539400
0#
b0000000000010100101101001011010010110100 %
b001011 '
1(
#558000
0(
b00000000000000000000000000001011 -
#576600
b0000000000001010010110100101101001011010 %
b001100 '
1(
#595200
0(
b00000000000000000000000000001100 -
#613800
1#
b0000000000000101001011010010110100101101 %
b001101 '
1(
#632400
0(
b00000000000000000000000000001101 -
#651000
0#
b0000000000000010100101101001011010010110 %
b001110 '
1(
#669600
0(
b00000000000000000000000000001110 -
#688200
1#
b0000000000000001010010110100101101001011 %
b001111 '
1(
#706800
0(
b00000000000000000000000000001111 -
#725400
b0000000000000000101001011010010110100101 %
b010000 '
1(
#744000
0(
b00000000000000000000000000010000 -
#762600
0#
b0000000000000000010100101101001011010010 %
b010001 '
1(
#781200
0(
b00000000000000000000000000010001 -
#799800
1#
b0000000000000000001010010110100101101001 %
b010010 '
1(
#818400
0(
b00000000000000000000000000010010 -
#837000
0#
b0000000000000000000101001011010010110100 %
b010011 '
1(
#855600
0(
b00000000000000000000000000010011 -
#874200
b0000000000000000000010100101101001011010 %
b010100 '
1(
#892800
0(
b00000000000000000000000000010100 -
#911400
1#
b0000000000000000000001010010110100101101 %
b010101 '
1(
#930000
0(
b00000000000000000000000000010101 -
#948600
0#
b0000000000000000000000101001011010010110 %
b010110 '
1(
#967200
0(
b00000000000000000000000000010110 -
#985800
1#
b0000000000000000000000010100101101001011 %
b010111 '
1(
#1004400
0(
b00000000000000000000000000010111 -
#1023000
b0000000000000000000000001010010110100101 %
b011000 '
1(
#1041600
0(
b00000000000000000000000000011000 -
#1060200
0#
b0000000000000000000000000101001011010010 %
b011001 '
1(
#1078800
0(
b00000000000000000000000000011001 -
#1097400
1#
b0000000000000000000000000010100101101001 %
b011010 '
1(
#1116000
0(
b00000000000000000000000000011010 -
#1134600
0#
b0000000000000000000000000001010010110100 %
b011011 '
1(
#1153200
0(
b00000000000000000000000000011011 -
#1171800
b0000000000000000000000000000101001011010 %
b011100 '
1(
#1190400
0(
b00000000000000000000000000011100 -
#1209000
1#
b0000000000000000000000000000010100101101 %
b011101 '
1(
#1227600
0(
b00000000000000000000000000011101 -
#1246200
0#
b0000000000000000000000000000001010010110 %
b011110 '
1(
#1264800
0(
b00000000000000000000000000011110 -
#1283400
1#
b0000000000000000000000000000000101001011 %
b011111 '
1(
#1302000
0(
b00000000000000000000000000011111 -
#1320600
b0000000000000000000000000000000010100101 %
b100000 '
1(
#1339200
0(
b00000000000000000000000000100000 -
#1357800
0#
b0000000000000000000000000000000001010010 %
b100001 '
1(
#1376400
0(
b00000000000000000000000000100001 -
#1395000
1#
b0000000000000000000000000000000000101001 %
b100010 '
1(
#1413600
0(
b00000000000000000000000000100010 -
#1432200
0#
b0000000000000000000000000000000000010100 %
b100011 '
1(
#1450800
0(
b00000000000000000000000000100011 -
#1469400
b0000000000000000000000000000000000001010 %
b100100 '
1(
#1488000
0(
b00000000000000000000000000100100 -
#1506600
1#
b0000000000000000000000000000000000000101 %
b100101 '
1(
#1525200
0(
b00000000000000000000000000100101 -
#1543800
0#
b0000000000000000000000000000000000000010 %
b100110 '
1(
#1562400
0(
b00000000000000000000000000100110 -
#1581000
1#
b0000000000000000000000000000000000000001 %
b100111 '
1(
#1599600
0(
b00000000000000000000000000100111 -
#1618200
0#
0$
b0000000000000000000000000000000000000000 %
b101000 '
1(
#1636800
0(
b00000000000000000000000000101000 -
