ALU/design.sv
module ALU (
    input  logic clk,          // System clock (SCLK)
    input  logic enable,       // Enable ALU operation
    input  logic clear,        // Active-high clear/reset
    input  logic [7:0] current_data_addr,
    input  logic [15:0] data,  // Input data (from Data Memory)
    input  logic [15:0] coeff_data, // Coefficient (from Coefficient Memory)
    input  logic [7:0] rj_data,// Rj value (from Rj Memory)
    output logic [7:0] data_addr, // Data Memory address (LSBs of coeff)
    output logic [8:0] coeff_addr, // Coefficient Memory address
    output logic [3:0] rj_addr,    // Rj Memory address
    output logic [39:0] accum_reg,        // 40-bit accumulator/shift register
    output logic output_en
);

//--------------------------------------------------------------
// Internal Signals
//--------------------------------------------------------------

logic [23:0] alu_result;       // Adder/subtractor result
logic [7:0] u_limit;           // Number of coefficients per Rj
logic [7:0] current_u_index;   // Coefficient counter for current Rj
logic accum_en, shift_en;      // Control signals from FSM
logic u_complete, rj_done, last_u;     // Status flags
logic first_rj;                // Flag to handle first Rj initialization

//--------------------------------------------------------------
// Control FSM (Manages accumulation and shift states)
//--------------------------------------------------------------
ALU_Control control (
    .clk(clk),
    .clear(clear),
    .enable(enable),
    .u_complete(u_complete),
    .last_u(last_u),
    .rj_done(rj_done),
    .accum_en(accum_en),
    .shift_en(shift_en),
    .output_en(output_en)
);

//--------------------------------------------------------------
// Adder/Subtractor (24-bit with sign extension)
//--------------------------------------------------------------
Adder adder (
    .operand1(accum_reg[39:16]),
    .operand2(data),
    .sub(coeff_data[8]),
    .result(alu_result)
);

//--------------------------------------------------------------
// Accumulator and Shift Logic
//--------------------------------------------------------------
always_ff @(posedge clk or posedge clear) begin
    if (clear) begin
        accum_reg <= 40'h0;
    end else begin
        if (accum_en) begin
            accum_reg[39:16] <= alu_result;
        end else if (shift_en) begin
            accum_reg <= {accum_reg[39], accum_reg[39:1]};
        end
    end
end

//--------------------------------------------------------------
// Rj and Coefficient Tracking
//--------------------------------------------------------------
always_ff @(posedge clk or posedge clear) begin
    if (clear) begin
        current_u_index <= 8'h1;
        coeff_addr <= 8'h0;
        u_limit         <= 8'h0;
        rj_addr         <= 4'h0;
        first_rj        <= 1'b1; // Initialize first Rj flag
    end else begin
        if (shift_en) begin
            // Load new Rj after shift
                        rj_addr         <= rj_addr + 1;
            u_limit         <= rj_data;
            current_u_index <= 8'h1;


            first_rj        <= 1'b0;
        end else if (first_rj && accum_en) begin
            // Load first Rj on first accumulation cycle
            u_limit         <= rj_data;
            first_rj        <= 1'b0;
        end else if (accum_en) begin
            // Track coefficients for current Rj
            current_u_index <= current_u_index + 1;
            
            coeff_addr <= coeff_addr + 1;
            
        end
    end
end

//--------------------------------------------------------------
// Address Generation and Status Flags
//--------------------------------------------------------------
assign data_addr  = (current_data_addr - 1)- coeff_data[7:0];
//assign coeff_addr = current_u_index; // Increments during ACCUM
assign u_complete = (current_u_index == rj_data);
assign rj_done    = (rj_addr == 4'd15); // Terminate after 16 Rj entries
assign last_u = u_complete && coeff_addr == 'd511;

endmodule

module ALU_Control (
    input  logic clk,
    input  logic clear,
    input  logic enable,
    input  logic u_complete,  // All coefficients processed for current Rj
    input  logic rj_done,     // All Rj entries processed\
    input  logic last_u,
    output logic accum_en,    // Enable accumulation
    output logic shift_en,     // Enable shift
    output logic output_en
);

//--------------------------------------------------------------
// State Definitions
//--------------------------------------------------------------
//One clock cycle could be saved
typedef enum {
    INIT = 0,   // Idle state
    ACCUM = 1,  // Accumulate coefficients
    SHIFT = 2,   // Shift after Rj completion
    FINAL_SHIFT = 3,
    DONE = 4
} state_e;

state_e state, next_state;

//--------------------------------------------------------------
// State Transitions
//--------------------------------------------------------------
always_ff @(posedge clk or posedge clear) begin
    if (clear) state <= INIT;
    else       state <= next_state;
end

always_comb begin
    case (state)
        INIT:  next_state = (enable) ? ACCUM : INIT;  // Start on enable
        ACCUM: begin
            if (u_complete) begin
                if(last_u) begin
                    next_state = FINAL_SHIFT;
                end
                else begin
                    next_state = SHIFT;
                end
            end
            else begin
                next_state = ACCUM;
            end
        end
        SHIFT: next_state = (rj_done) ? INIT : ACCUM; // Loop or terminate
        FINAL_SHIFT: next_state = DONE;
        DONE: next_state = DONE;
        default: next_state = INIT;
    endcase
end


//--------------------------------------------------------------
// Output Logic
//--------------------------------------------------------------
assign accum_en = (state == ACCUM); // Accumulate in ACCUM state
assign shift_en = (state == SHIFT) || (state == FINAL_SHIFT); // Shift in SHIFT state
assign output_en = (state == DONE);
endmodule

module Adder (
    input  logic [23:0] operand1, // Upper 24 bits of accumulator
    input  logic [15:0] operand2, // Input data (sign-extended)
    input  logic sub,             // Subtract if coefficient MSB=1
    output logic [23:0] result    // Result to accumulator
);

//--------------------------------------------------------------
// Sign-Extend Input Data to 24 Bits
//--------------------------------------------------------------
logic [23:0] sign_ext_data;
assign sign_ext_data = {{8{operand2[15]}}, operand2}; // 16 → 24 bits

//--------------------------------------------------------------
// Addition/Subtraction Logic
//--------------------------------------------------------------
always_comb begin
    if (sub) result = operand1 - sign_ext_data; // Subtract
    else     result = operand1 + sign_ext_data; // Add
end

endmodule

ALU/tb.sv
`timescale 1ns / 1ps

module tb_ALU;

    // Inputs
    logic clk;
    logic enable;
    logic clear, output_en;
    logic [15:0] data;
    logic [15:0] coeff_data;
    logic [7:0] rj_data;

    // Outputs
    logic [7:0] data_addr;
    logic [8:0] coeff_addr;
    logic [3:0] rj_addr;

    // Memory arrays
    logic [15:0] data_mem [0:255];  // Data memory (256x16)
    logic [15:0] coeff_mem [0:511]; // Coefficient memory (512x16)
    logic [7:0] rj_mem [0:15];      // Rj memory (16x8)

    // Read data from memory
    assign data = data_mem[data_addr];
    assign coeff_data = coeff_mem[coeff_addr];
    assign rj_data = rj_mem[rj_addr];

    // Instantiate the ALU
    ALU uut (
        .clk(clk),
        .enable(enable),
        .clear(clear),
        .current_data_addr(3),
        .data(data),
        .coeff_data(coeff_data),
        .rj_data(rj_data),
        .data_addr(data_addr),
        .coeff_addr(coeff_addr),
        .rj_addr(rj_addr),
        .output_en(output_en)
    );

    // Clock generation
    initial begin
        clk = 0;
        forever #5 clk = ~clk;  // 100 MHz clock
    end

    // Load memory files
    initial begin
        $readmemh("data.hex", data_mem);     // Load data memory
        $readmemh("coeff.hex", coeff_mem);   // Load coefficient memory
        $readmemh("rj_in.hex", rj_mem);         // Load Rj memory
    end

    // Test sequence
    initial begin
        // Initialize inputs
        enable = 0;
        clear = 1;
        #20 clear = 0;  // Release reset

        // Enable ALU
        enable = 1;

        
        

        // Wait for ALU to process
        #6000;

        // Display results
        $display("data_addr = 0x%h, coeff_addr = 0x%h, rj_addr = 0x%h",
                    data_addr, coeff_addr, rj_addr);
        

        // Disable ALU
        enable = 0;

        // End simulation
        #100 $finish;
    end
    initial begin
        $dumpfile("tb.vcd");
        $dumpvars(0, tb_ALU);
    end

endmodule

ALU/tb.vcd
$version Generated by VerilatedVcd $end
$timescale 1ps $end
 $scope module $rootio $end
 $upscope $end
 $scope module tb_ALU $end
  $var wire 1 E clk $end
  $var wire 1 F enable $end
  $var wire 1 G clear $end
  $var wire 1 3 output_en $end
  $var wire 16 H data [15:0] $end
  $var wire 16 I coeff_data [15:0] $end
  $var wire 8 4 rj_data [7:0] $end
  $var wire 8 5 data_addr [7:0] $end
  $var wire 9 6 coeff_addr [8:0] $end
  $var wire 4 7 rj_addr [3:0] $end
  $var wire 8 # rj_mem[0] [7:0] $end
  $var wire 8 $ rj_mem[1] [7:0] $end
  $var wire 8 % rj_mem[2] [7:0] $end
  $var wire 8 & rj_mem[3] [7:0] $end
  $var wire 8 ' rj_mem[4] [7:0] $end
  $var wire 8 ( rj_mem[5] [7:0] $end
  $var wire 8 ) rj_mem[6] [7:0] $end
  $var wire 8 * rj_mem[7] [7:0] $end
  $var wire 8 + rj_mem[8] [7:0] $end
  $var wire 8 , rj_mem[9] [7:0] $end
  $var wire 8 - rj_mem[10] [7:0] $end
  $var wire 8 . rj_mem[11] [7:0] $end
  $var wire 8 / rj_mem[12] [7:0] $end
  $var wire 8 0 rj_mem[13] [7:0] $end
  $var wire 8 1 rj_mem[14] [7:0] $end
  $var wire 8 2 rj_mem[15] [7:0] $end
  $scope module uut $end
   $var wire 1 E clk $end
   $var wire 1 F enable $end
   $var wire 1 G clear $end
   $var wire 8 M current_data_addr [7:0] $end
   $var wire 16 H data [15:0] $end
   $var wire 16 I coeff_data [15:0] $end
   $var wire 8 4 rj_data [7:0] $end
   $var wire 8 5 data_addr [7:0] $end
   $var wire 9 6 coeff_addr [8:0] $end
   $var wire 4 7 rj_addr [3:0] $end
   $var wire 1 3 output_en $end
   $var wire 40 8 accum_reg [39:0] $end
   $var wire 24 J alu_result [23:0] $end
   $var wire 8 : u_limit [7:0] $end
   $var wire 8 ; current_u_index [7:0] $end
   $var wire 1 < accum_en $end
   $var wire 1 = shift_en $end
   $var wire 1 > u_complete $end
   $var wire 1 ? rj_done $end
   $var wire 1 @ last_u $end
   $var wire 1 A first_rj $end
   $scope module adder $end
    $var wire 24 B operand1 [23:0] $end
    $var wire 16 H operand2 [15:0] $end
    $var wire 1 K sub $end
    $var wire 24 J result [23:0] $end
    $var wire 24 C sign_ext_data [23:0] $end
   $upscope $end
   $scope module control $end
    $var wire 1 E clk $end
    $var wire 1 G clear $end
    $var wire 1 F enable $end
    $var wire 1 > u_complete $end
    $var wire 1 ? rj_done $end
    $var wire 1 @ last_u $end
    $var wire 1 < accum_en $end
    $var wire 1 = shift_en $end
    $var wire 1 3 output_en $end
    $var wire 32 D state [31:0] $end
    $var wire 32 L next_state [31:0] $end
   $upscope $end
  $upscope $end
 $upscope $end
$enddefinitions $end


#0
b00111110 #
b00101110 $
b00100110 %
b00000101 &
b00110100 '
b00001011 (
b00000111 )
b00101000 *
b00000111 +
b00101110 ,
b01000111 -
b00111011 .
b00100011 /
b00000110 0
b00001001 1
b00010010 2
03
b00111110 4
b00101111 5
b000000000 6
b0000 7
b0000000000000000000000000000000000000000 8
b00000000 :
b00000000 ;
0<
0=
0>
0?
0@
0A
b000000000000000000000000 B
b000000000000000000000000 C
b00000000000000000000000000000000 D
0E
0F
1G
b0000000000000000 H
b0000000011010011 I
b000000000000000000000000 J
0K
b00000000000000000000000000000000 L
b00000011 M
#5000
b00000001 ;
1A
1E
#10000
0E
#15000
1E
#20000
0E
1F
0G
b00000000000000000000000000000001 L
#25000
1<
b00000000000000000000000000000001 D
1E
#30000
0E
#35000
b00111110 :
0A
1E
#40000
0E
#45000
b11101100 5
b000000001 6
b00000010 ;
1E
b0000000100010110 I
1K
#50000
0E
#55000
b000000010 6
b00000011 ;
1E
b0000000000010110 I
0K
#60000
0E
#65000
b00110010 5
b000000011 6
b00000100 ;
1E
b0000000111010000 I
1K
#70000
0E
#75000
b11000101 5
b000000100 6
b00000101 ;
1E
b0000000000111101 I
0K
#80000
0E
#85000
b11011011 5
b000000101 6
b00000110 ;
1E
b0000000000100111 I
#90000
0E
#95000
b01001001 5
b000000110 6
b00000111 ;
1E
b0000000110111001 I
1K
#100000
0E
#105000
b11000000 5
b000000111 6
b00001000 ;
1E
b0000000001000010 I
0K
#110000
0E
#115000
b00011101 5
b000001000 6
b00001001 ;
1E
b0000000011100101 I
#120000
0E
#125000
b01101000 5
b000001001 6
b00001010 ;
1E
b0000000110011010 I
1K
#130000
0E
#135000
b11111000 5
b000001010 6
b00001011 ;
1E
b0000000000001010 I
0K
#140000
0E
#145000
b11100101 5
b000001011 6
b00001100 ;
1E
b0000000100011101 I
1K
#150000
0E
#155000
b01010101 5
b000001100 6
b00001101 ;
1E
b0000000010101101 I
0K
#160000
0E
#165000
b11010010 5
b000001101 6
b00001110 ;
1E
b0000000100110000 I
1K
#170000
0E
#175000
b00001111 5
b000001110 6
b00001111 ;
1E
b0000000011110011 I
0K
#180000
0E
#185000
b10110000 5
b000001111 6
b00010000 ;
1E
b0000000001010010 I
#190000
0E
#195000
b11011000 5
b000010000 6
b00010001 ;
1E
b0000000000101010 I
#200000
0E
#205000
b10100000 5
b000010001 6
b00010010 ;
1E
b0000000101100010 I
1K
#210000
0E
#215000
b00100100 5
b000010010 6
b00010011 ;
1E
b0000000011011110 I
0K
#220000
0E
#225000
b10100101 5
b000010011 6
b00010100 ;
1E
b0000000101011101 I
1K
#230000
0E
#235000
b11011000 5
b000010100 6
b00010101 ;
1E
b0000000000101010 I
0K
#240000
0E
#245000
b00000110 5
b000010101 6
b00010110 ;
1E
b0000000011111100 I
#250000
0E
#255000
b00010100 5
b000010110 6
b00010111 ;
1E
b0000000111101110 I
1K
#260000
0E
#265000
b10101100 5
b000010111 6
b00011000 ;
1E
b0000000101010110 I
#270000
0E
#275000
b11100110 5
b000011000 6
b00011001 ;
1E
b0000000000011100 I
0K
#280000
0E
#285000
b00000001 5
b000011001 6
b00011010 ;
b111111111001000100001111 C
1E
b1001000100001111 H
b0000000100000001 I
b000000000110111011110001 J
1K
#290000
0E
#295000
b10101111 5
b000011010 6
b0000000001101110111100010000000000000000 8
b00011011 ;
b000000000110111011110001 B
b000000000000000000000000 C
1E
b0000000000000000 H
b0000000001010011 I
0K
#300000
0E
#305000
b10101001 5
b000011011 6
b00011100 ;
1E
b0000000101011001 I
1K
#310000
0E
#315000
b00001110 5
b000011100 6
b00011101 ;
1E
b0000000011110100 I
0K
#320000
0E
#325000
b11000000 5
b000011101 6
b00011110 ;
1E
b0000000101000010 I
1K
#330000
0E
#335000
b00110011 5
b000011110 6
b00011111 ;
1E
b0000000111001111 I
#340000
0E
#345000
b00001101 5
b000011111 6
b00100000 ;
1E
b0000000111110101 I
#350000
0E
#355000
b01100111 5
b000100000 6
b00100001 ;
1E
b0000000110011011 I
#360000
0E
#365000
b01111001 5
b000100001 6
b00100010 ;
1E
b0000000110001001 I
#370000
0E
#375000
b10010001 5
b000100010 6
b00100011 ;
1E
b0000000001110001 I
0K
#380000
0E
#385000
b10010111 5
b000100011 6
b00100100 ;
1E
b0000000001101011 I
#390000
0E
#395000
b11000111 5
b000100100 6
b00100101 ;
1E
b0000000000111011 I
#400000
0E
#405000
b00110100 5
b000100101 6
b00100110 ;
1E
b0000000011001110 I
#410000
0E
#415000
b10101011 5
b000100110 6
b00100111 ;
1E
b0000000001010111 I
#420000
0E
#425000
b01111111 5
b000100111 6
b00101000 ;
1E
b0000000010000011 I
#430000
0E
#435000
b01110100 5
b000101000 6
b00101001 ;
1E
b0000000010001110 I
#440000
0E
#445000
b10010011 5
b000101001 6
b00101010 ;
1E
b0000000101101111 I
1K
#450000
0E
#455000
b10111111 5
b000101010 6
b00101011 ;
1E
b0000000101000011 I
#460000
0E
#465000
b01000101 5
b000101011 6
b00101100 ;
1E
b0000000010111101 I
0K
#470000
0E
#475000
b10011101 5
b000101100 6
b00101101 ;
1E
b0000000101100101 I
1K
#480000
0E
#485000
b00111111 5
b000101101 6
b00101110 ;
1E
b0000000111000011 I
#490000
0E
#495000
b10001111 5
b000101110 6
b00101111 ;
1E
b0000000101110011 I
#500000
0E
#505000
b00100100 5
b000101111 6
b00110000 ;
1E
b0000000011011110 I
0K
#510000
0E
#515000
b10110101 5
b000110000 6
b00110001 ;
1E
b0000000001001101 I
#520000
0E
#525000
b00001010 5
b000110001 6
b00110010 ;
1E
b0000000111111000 I
1K
#530000
0E
#535000
b11111111 5
b000110010 6
b00110011 ;
1E
b0000000000000011 I
0K
#540000
0E
#545000
b11101101 5
b000110011 6
b00110100 ;
1E
b0000000100010101 I
1K
#550000
0E
#555000
b01100110 5
b000110100 6
b00110101 ;
1E
b0000000110011100 I
#560000
0E
#565000
b11111000 5
b000110101 6
b00110110 ;
1E
b0000000100001010 I
#570000
0E
#575000
b11110110 5
b000110110 6
b00110111 ;
1E
b0000000100001100 I
#580000
0E
#585000
b01111111 5
b000110111 6
b00111000 ;
1E
b0000000110000011 I
#590000
0E
#595000
b10110001 5
b000111000 6
b00111001 ;
1E
b0000000101010001 I
#600000
0E
#605000
b11101110 5
b000111001 6
b00111010 ;
1E
b0000000000010100 I
0K
#610000
0E
#615000
b01100111 5
b000111010 6
b00111011 ;
1E
b0000000010011011 I
#620000
0E
#625000
b10010110 5
b000111011 6
b00111100 ;
1E
b0000000001101100 I
#630000
0E
#635000
b11000110 5
b000111100 6
b00111101 ;
1E
b0000000100111100 I
1K
#640000
0E
#645000
b00001110 5
b000111101 6
b00111110 ;
1>
1E
b0000000111110100 I
b00000000000000000000000000000010 L
#650000
0E
#655000
b10010011 5
b000111110 6
b00111111 ;
0<
1=
0>
b00000000000000000000000000000010 D
1E
b0000000101101111 I
b00000000000000000000000000000001 L
#660000
0E
#665000
b00101110 4
b0001 7
b0000000000110111011110001000000000000000 8
b00000001 ;
1<
0=
b000000000011011101111000 B
b00000000000000000000000000000001 D
1E
b000000000011011101111000 J
#670000
0E
#675000
b11001110 5
b000111111 6
b00000010 ;
1E
b0000000000110100 I
0K
#680000
0E
#685000
b01010000 5
b001000000 6
b00000011 ;
1E
b0000000110110010 I
1K
#690000
0E
#695000
b10110100 5
b001000001 6
b00000100 ;
1E
b0000000001001110 I
0K
#700000
0E
#705000
b01101101 5
b001000010 6
b00000101 ;
1E
b0000000110010101 I
1K
#710000
0E
#715000
b00011010 5
b001000011 6
b00000110 ;
1E
b0000000011101000 I
0K
#720000
0E
#725000
b11011001 5
b001000100 6
b00000111 ;
1E
b0000000000101001 I
#730000
0E
#735000
b00111011 5
b001000101 6
b00001000 ;
1E
b0000000111000111 I
1K
#740000
0E
#745000
b10101000 5
b001000110 6
b00001001 ;
1E
b0000000101011010 I
#750000
0E
#755000
b01011001 5
b001000111 6
b00001010 ;
1E
b0000000010101001 I
0K
#760000
0E
#765000
b10111011 5
b001001000 6
b00001011 ;
1E
b0000000001000111 I
#770000
0E
#775000
b01001011 5
b001001001 6
b00001100 ;
1E
b0000000010110111 I
#780000
0E
#785000
b11010010 5
b001001010 6
b00001101 ;
1E
b0000000000110000 I
#790000
0E
#795000
b01011100 5
b001001011 6
b00001110 ;
1E
b0000000110100110 I
1K
#800000
0E
#805000
b01101011 5
b001001100 6
b00001111 ;
1E
b0000000010010111 I
0K
#810000
0E
#815000
b10000011 5
b001001101 6
b00010000 ;
1E
b0000000101111111 I
1K
#820000
0E
#825000
b10111001 5
b001001110 6
b00010001 ;
1E
b0000000001001001 I
0K
#830000
0E
#835000
b10010010 5
b001001111 6
b00010010 ;
1E
b0000000101110000 I
1K
#840000
0E
#845000
b11011101 5
b001010000 6
b00010011 ;
1E
b0000000000100101 I
0K
#850000
0E
#855000
b00011101 5
b001010001 6
b00010100 ;
1E
b0000000011100101 I
#860000
0E
#865000
b11010101 5
b001010010 6
b00010101 ;
1E
b0000000100101101 I
1K
#870000
0E
#875000
b00110111 5
b001010011 6
b00010110 ;
1E
b0000000111001011 I
#880000
0E
#885000
b01101011 5
b001010100 6
b00010111 ;
1E
b0000000010010111 I
0K
#890000
0E
#895000
b01010011 5
b001010101 6
b00011000 ;
1E
b0000000110101111 I
1K
#900000
0E
#905000
b10110000 5
b001010110 6
b00011001 ;
1E
b0000000001010010 I
0K
#910000
0E
#915000
b11000101 5
b001010111 6
b00011010 ;
1E
b0000000100111101 I
1K
#920000
0E
#925000
b11100000 5
b001011000 6
b00011011 ;
1E
b0000000100100010 I
#930000
0E
#935000
b10011011 5
b001011001 6
b00011100 ;
1E
b0000000101100111 I
#940000
0E
#945000
b11111101 5
b001011010 6
b00011101 ;
1E
b0000000100000101 I
#950000
0E
#955000
b11111110 5
b001011011 6
b00011110 ;
1E
b0000000100000100 I
#960000
0E
#965000
b01111101 5
b001011100 6
b00011111 ;
1E
b0000000110000101 I
#970000
0E
#975000
b00101001 5
b001011101 6
b00100000 ;
1E
b0000000011011001 I
0K
#980000
0E
#985000
b10000110 5
b001011110 6
b00100001 ;
1E
b0000000001111100 I
#990000
0E
#995000
b00111100 5
b001011111 6
b00100010 ;
1E
b0000000011000110 I
#1000000
0E
#1005000
b01100110 5
b001100000 6
b00100011 ;
1E
b0000000110011100 I
1K
#1010000
0E
#1015000
b00101111 5
b001100001 6
b00100100 ;
1E
b0000000011010011 I
0K
#1020000
0E
#1025000
b11111010 5
b001100010 6
b00100101 ;
1E
b0000000100001000 I
1K
#1030000
0E
#1035000
b00001001 5
b001100011 6
b00100110 ;
1E
b0000000111111001 I
#1040000
0E
#1045000
b01001100 5
b001100100 6
b00100111 ;
1E
b0000000110110110 I
#1050000
0E
#1055000
b00010010 5
b001100101 6
b00101000 ;
1E
b0000000111110000 I
#1060000
0E
#1065000
b10001000 5
b001100110 6
b00101001 ;
1E
b0000000101111010 I
#1070000
0E
#1075000
b00110100 5
b001100111 6
b00101010 ;
1E
b0000000011001110 I
0K
#1080000
0E
#1085000
b11011000 5
b001101000 6
b00101011 ;
1E
b0000000000101010 I
#1090000
0E
#1095000
b10100100 5
b001101001 6
b00101100 ;
1E
b0000000101011110 I
1K
#1100000
0E
#1105000
b11101010 5
b001101010 6
b00101101 ;
1E
b0000000000011000 I
0K
#1110000
0E
#1115000
b11000110 5
b001101011 6
b00101110 ;
1>
1E
b0000000000111100 I
b00000000000000000000000000000010 L
#1120000
0E
#1125000
b11001011 5
b001101100 6
b00101111 ;
0<
1=
0>
b00000000000000000000000000000010 D
1E
b0000000000110111 I
b00000000000000000000000000000001 L
#1130000
0E
#1135000
b00100110 4
b0010 7
b0000000000011011101111000100000000000000 8
b00101110 :
b00000001 ;
1<
0=
b000000000001101110111100 B
b00000000000000000000000000000001 D
1E
b000000000001101110111100 J
#1140000
0E
#1145000
b01010011 5
b001101101 6
b00000010 ;
1E
b0000000010101111 I
#1150000
0E
#1155000
b00010000 5
b001101110 6
b00000011 ;
1E
b0000000111110010 I
1K
#1160000
0E
#1165000
b01001111 5
b001101111 6
b00000100 ;
1E
b0000000110110011 I
#1170000
0E
#1175000
b01110010 5
b001110000 6
b00000101 ;
1E
b0000000110010000 I
#1180000
0E
#1185000
b10001100 5
b001110001 6
b00000110 ;
1E
b0000000101110110 I
#1190000
0E
#1195000
b00110010 5
b001110010 6
b00000111 ;
1E
b0000000111010000 I
#1200000
0E
#1205000
b11000001 5
b001110011 6
b00001000 ;
1E
b0000000101000001 I
#1210000
0E
#1215000
b11001000 5
b001110100 6
b00001001 ;
1E
b0000000100111010 I
#1220000
0E
#1225000
b11100001 5
b001110101 6
b00001010 ;
1E
b0000000100100001 I
#1230000
0E
#1235000
b11011110 5
b001110110 6
b00001011 ;
1E
b0000000000100100 I
0K
#1240000
0E
#1245000
b01001011 5
b001110111 6
b00001100 ;
1E
b0000000010110111 I
#1250000
0E
#1255000
b00001110 5
b001111000 6
b00001101 ;
1E
b0000000011110100 I
#1260000
0E
#1265000
b10111000 5
b001111001 6
b00001110 ;
1E
b0000000101001010 I
1K
#1270000
0E
#1275000
b01101001 5
b001111010 6
b00001111 ;
1E
b0000000010011001 I
0K
#1280000
0E
#1285000
b01100001 5
b001111011 6
b00010000 ;
1E
b0000000010100001 I
#1290000
0E
#1295000
b10101111 5
b001111100 6
b00010001 ;
1E
b0000000001010011 I
#1300000
0E
#1305000
b11000101 5
b001111101 6
b00010010 ;
1E
b0000000100111101 I
1K
#1310000
0E
#1315000
b11011111 5
b001111110 6
b00010011 ;
1E
b0000000100100011 I
#1320000
0E
#1325000
b11100111 5
b001111111 6
b00010100 ;
1E
b0000000000011011 I
0K
#1330000
0E
#1335000
b00011011 5
b010000000 6
b00010101 ;
1E
b0000000011100111 I
#1340000
0E
#1345000
b10111010 5
b010000001 6
b00010110 ;
1E
b0000000101001000 I
1K
#1350000
0E
#1355000
b10000101 5
b010000010 6
b00010111 ;
1E
b0000000101111101 I
#1360000
0E
#1365000
b00100001 5
b010000011 6
b00011000 ;
1E
b0000000111100001 I
#1370000
0E
#1375000
b10000110 5
b010000100 6
b00011001 ;
1E
b0000000101111100 I
#1380000
0E
#1385000
b11101101 5
b010000101 6
b00011010 ;
1E
b0000000000010101 I
0K
#1390000
0E
#1395000
b10011100 5
b010000110 6
b00011011 ;
1E
b0000000001100110 I
#1400000
0E
#1405000
b11010110 5
b010000111 6
b00011100 ;
1E
b0000000000101100 I
#1410000
0E
#1415000
b01100001 5
b010001000 6
b00011101 ;
1E
b0000000010100001 I
#1420000
0E
#1425000
b11000010 5
b010001001 6
b00011110 ;
1E
b0000000101000000 I
1K
#1430000
0E
#1435000
b01001010 5
b010001010 6
b00011111 ;
1E
b0000000010111000 I
0K
#1440000
0E
#1445000
b10000101 5
b010001011 6
b00100000 ;
1E
b0000000101111101 I
1K
#1450000
0E
#1455000
b10010110 5
b010001100 6
b00100001 ;
1E
b0000000001101100 I
0K
#1460000
0E
#1465000
b01001110 5
b010001101 6
b00100010 ;
1E
b0000000110110100 I
1K
#1470000
0E
#1475000
b11100101 5
b010001110 6
b00100011 ;
1E
b0000000000011101 I
0K
#1480000
0E
#1485000
b10101110 5
b010001111 6
b00100100 ;
1E
b0000000001010100 I
#1490000
0E
#1495000
b00000110 5
b010010000 6
b00100101 ;
1E
b0000000111111100 I
1K
#1500000
0E
#1505000
b00000000 5
b010010001 6
b00100110 ;
1>
b000000000100101111001000 C
1E
b0100101111001000 H
b0000000000000010 I
b000000000110011110000100 J
0K
b00000000000000000000000000000010 L
#1510000
0E
#1515000
b01000110 5
b010010010 6
b0000000001100111100001000100000000000000 8
b00100111 ;
0<
1=
0>
b000000000110011110000100 B
b000000000000000000000000 C
b00000000000000000000000000000010 D
1E
b0000000000000000 H
b0000000110111100 I
1K
b00000000000000000000000000000001 L
#1520000
0E
#1525000
b00000101 4
b0011 7
b0000000000110011110000100010000000000000 8
b00100110 :
b00000001 ;
1<
0=
b000000000011001111000010 B
b00000000000000000000000000000001 D
1E
b000000000011001111000010 J
#1530000
0E
#1535000
b11010011 5
b010010011 6
b00000010 ;
1E
b0000000000101111 I
0K
#1540000
0E
#1545000
b11101000 5
b010010100 6
b00000011 ;
1E
b0000000100011010 I
1K
#1550000
0E
#1555000
b01011010 5
b010010101 6
b00000100 ;
1E
b0000000010101000 I
0K
#1560000
0E
#1565000
b11010011 5
b010010110 6
b00000101 ;
1>
1E
b0000000100101111 I
1K
b00000000000000000000000000000010 L
#1570000
0E
#1575000
b00000110 5
b010010111 6
b00000110 ;
0<
1=
0>
b00000000000000000000000000000010 D
1E
b0000000011111100 I
0K
b00000000000000000000000000000001 L
#1580000
0E
#1585000
b00110100 4
b0100 7
b0000000000011001111000010001000000000000 8
b00000101 :
b00000001 ;
1<
0=
b000000000001100111100001 B
b00000000000000000000000000000001 D
1E
b000000000001100111100001 J
#1590000
0E
#1595000
b00111011 5
b010011000 6
b00000010 ;
1E
b0000000011000111 I
#1600000
0E
#1605000
b00001010 5
b010011001 6
b00000011 ;
1E
b0000000011111000 I
#1610000
0E
#1615000
b00101011 5
b010011010 6
b00000100 ;
1E
b0000000011010111 I
#1620000
0E
#1625000
b01101011 5
b010011011 6
b00000101 ;
1E
b0000000010010111 I
#1630000
0E
#1635000
b11010101 5
b010011100 6
b00000110 ;
1E
b0000000100101101 I
1K
#1640000
0E
#1645000
b11011001 5
b010011101 6
b00000111 ;
1E
b0000000100101001 I
#1650000
0E
#1655000
b11111110 5
b010011110 6
b00001000 ;
1E
b0000000100000100 I
#1660000
0E
#1665000
b11111000 5
b010011111 6
b00001001 ;
1E
b0000000100001010 I
#1670000
0E
#1675000
b00011110 5
b010100000 6
b00001010 ;
1E
b0000000111100100 I
#1680000
0E
#1685000
b11001111 5
b010100001 6
b00001011 ;
1E
b0000000100110011 I
#1690000
0E
#1695000
b11000101 5
b010100010 6
b00001100 ;
1E
b0000000000111101 I
0K
#1700000
0E
#1705000
b00101101 5
b010100011 6
b00001101 ;
1E
b0000000011010101 I
#1710000
0E
#1715000
b00001001 5
b010100100 6
b00001110 ;
1E
b0000000011111001 I
#1720000
0E
#1725000
b10010111 5
b010100101 6
b00001111 ;
1E
b0000000001101011 I
#1730000
0E
#1735000
b00100100 5
b010100110 6
b00010000 ;
1E
b0000000111011110 I
1K
#1740000
0E
#1745000
b01000000 5
b010100111 6
b00010001 ;
1E
b0000000111000010 I
#1750000
0E
#1755000
b00110000 5
b010101000 6
b00010010 ;
1E
b0000000111010010 I
#1760000
0E
#1765000
b00101011 5
b010101001 6
b00010011 ;
1E
b0000000111010111 I
#1770000
0E
#1775000
b10110010 5
b010101010 6
b00010100 ;
1E
b0000000101010000 I
#1780000
0E
#1785000
b01000100 5
b010101011 6
b00010101 ;
1E
b0000000110111110 I
#1790000
0E
#1795000
b10011101 5
b010101100 6
b00010110 ;
1E
b0000000001100101 I
0K
#1800000
0E
#1805000
b00011010 5
b010101101 6
b00010111 ;
1E
b0000000011101000 I
#1810000
0E
#1815000
b00100011 5
b010101110 6
b00011000 ;
1E
b0000000111011111 I
1K
#1820000
0E
#1825000
b10110110 5
b010101111 6
b00011001 ;
1E
b0000000101001100 I
#1830000
0E
#1835000
b11011100 5
b010110000 6
b00011010 ;
1E
b0000000100100110 I
#1840000
0E
#1845000
b01110001 5
b010110001 6
b00011011 ;
1E
b0000000110010001 I
#1850000
0E
#1855000
b01001000 5
b010110010 6
b00011100 ;
1E
b0000000110111010 I
#1860000
0E
#1865000
b11111100 5
b010110011 6
b00011101 ;
1E
b0000000000000110 I
0K
#1870000
0E
#1875000
b11001010 5
b010110100 6
b00011110 ;
1E
b0000000000111000 I
#1880000
0E
#1885000
b00101100 5
b010110101 6
b00011111 ;
1E
b0000000011010110 I
#1890000
0E
#1895000
b00000010 5
b010110110 6
b00100000 ;
b000000000001111011011101 C
1E
b0001111011011101 H
b0000000100000000 I
b111111111111101100000100 J
1K
#1900000
0E
